eti_django_page_cms-1.8.6.dist-info/DESCRIPTION.rst
eti_django_page_cms-1.8.6.dist-info/METADATA
eti_django_page_cms-1.8.6.dist-info/metadata.json
eti_django_page_cms-1.8.6.dist-info/RECORD
eti_django_page_cms-1.8.6.dist-info/top_level.txt
eti_django_page_cms-1.8.6.dist-info/WHEEL
pages/__init__.py
pages/api.py
pages/app_config.py
pages/cache.py
pages/checks.py
pages/context_processors.py
pages/managers.py
pages/models.py
pages/phttp.py
pages/placeholders.py
pages/search_indexes.py
pages/serializers.py
pages/settings.py
pages/test_runner.py
pages/urlconf_registry.py
pages/urls.py
pages/utils.py
pages/views.py
pages/widgets.py
pages/widgets_registry.py
pages/admin/__init__.py
pages/admin/forms.py
pages/admin/utils.py
pages/admin/views.py
pages/fixtures/pages_tests.json
pages/locale/da/LC_MESSAGES/django.mo
pages/locale/da/LC_MESSAGES/django.po
pages/locale/de/LC_MESSAGES/django.mo
pages/locale/de/LC_MESSAGES/django.po
pages/locale/de/LC_MESSAGES/djangojs.mo
pages/locale/de/LC_MESSAGES/djangojs.po
pages/locale/en/LC_MESSAGES/django.mo
pages/locale/en/LC_MESSAGES/django.po
pages/locale/es/LC_MESSAGES/django.mo
pages/locale/es/LC_MESSAGES/django.po
pages/locale/fr/LC_MESSAGES/django.mo
pages/locale/fr/LC_MESSAGES/django.po
pages/locale/he/LC_MESSAGES/django.mo
pages/locale/he/LC_MESSAGES/django.po
pages/locale/it/LC_MESSAGES/django.mo
pages/locale/it/LC_MESSAGES/django.po
pages/locale/nl/LC_MESSAGES/django.mo
pages/locale/nl/LC_MESSAGES/django.po
pages/locale/ru/LC_MESSAGES/django.mo
pages/locale/ru/LC_MESSAGES/django.po
pages/locale/ru/LC_MESSAGES/djangojs.mo
pages/locale/ru/LC_MESSAGES/djangojs.po
pages/locale/sk/LC_MESSAGES/django.mo
pages/locale/sk/LC_MESSAGES/django.po
pages/management/__init__.py
pages/management/utils.py
pages/management/commands/__init__.py
pages/management/commands/pages_pull.py
pages/management/commands/pages_push.py
pages/migrations/0001_initial.py
pages/migrations/0002_page_sites.py
pages/migrations/0003_page_uuid.py
pages/migrations/0004_meta_options.py
pages/migrations/__init__.py
pages/plugins/__init__.py
pages/plugins/jsonexport/__init__.py
pages/plugins/jsonexport/actions.py
pages/plugins/jsonexport/admin_urls.py
pages/plugins/jsonexport/models.py
