Metadata-Version: 2.0
Name: eti-django-page-cms
Version: 1.8.6
Summary: A tree based Django CMS application
Home-page: https://github.com/localhuman/django-page-cms/
Author: Thomas Saunders
Author-email: saun0063@umn.edu
License: BSD
Download-URL: http://pypi.python.org/packages/source/d/eti-django-page-cms/eti-django-page-cms-1.8.6.tar.gz
Platform: UNKNOWN
Classifier: Development Status :: 5 - Production/Stable
Classifier: Environment :: Web Environment
Classifier: Intended Audience :: Developers
Classifier: License :: OSI Approved :: BSD License
Classifier: Operating System :: OS Independent
Classifier: Programming Language :: Python
Classifier: Framework :: Django
Classifier: Programming Language :: Python :: 2.7
Classifier: Programming Language :: Python :: 3.3
Classifier: Programming Language :: Python :: 3.4
Classifier: Programming Language :: Python :: 3.5
Classifier: Programming Language :: JavaScript
Classifier: Topic :: Internet :: WWW/HTTP :: Site Management
